atr/__init__.py
atr/access.py
atr/composition.py
atr/decorator.py
atr/executor.py
atr/health.py
atr/hf_utils.py
atr/injection.py
atr/metrics.py
atr/policies.py
atr/py.typed
atr/registry.py
atr/schema.py
agent_tool_registry-0.3.0.dist-info/METADATA
agent_tool_registry-0.3.0.dist-info/WHEEL
agent_tool_registry-0.3.0.dist-info/entry_points.txt
agent_tool_registry-0.3.0.dist-info/top_level.txt
agent_tool_registry-0.3.0.dist-info/RECORD
