Metadata-Version: 2.4
Name: agent-tool-registry
Version: 0.3.0
Summary: A decentralized marketplace for agent capabilities - The Hands of AI Agents
Home-page: https://github.com/imran-siddique/atr
Author: Agent Tool Registry Contributors
Author-email: Imran Siddique <imransiddique@live.com>
Maintainer-email: Imran Siddique <imransiddique@live.com>
License: MIT
Project-URL: Homepage, https://github.com/imran-siddique/atr
Project-URL: Repository, https://github.com/imran-siddique/atr
Project-URL: Documentation, https://github.com/imran-siddique/atr#readme
Project-URL: Issues, https://github.com/imran-siddique/atr/issues
Project-URL: Changelog, https://github.com/imran-siddique/atr/blob/main/CHANGELOG.md
Keywords: agent,tools,registry,llm,ai,function-calling,openai,anthropic
Classifier: Development Status :: 4 - Beta
Classifier: Intended Audience :: Developers
Classifier: Intended Audience :: Science/Research
Classifier: License :: OSI Approved :: MIT License
Classifier: Operating System :: OS Independent
Classifier: Programming Language :: Python :: 3
Classifier: Programming Language :: Python :: 3.9
Classifier: Programming Language :: Python :: 3.10
Classifier: Programming Language :: Python :: 3.11
Classifier: Programming Language :: Python :: 3.12
Classifier: Topic :: Scientific/Engineering :: Artificial Intelligence
Classifier: Topic :: Software Development :: Libraries :: Python Modules
Classifier: Typing :: Typed
Requires-Python: >=3.8
Requires-Dist: pydantic<3.0.0,>=2.0.0
Provides-Extra: sandbox
Requires-Dist: docker>=7.0.0; extra == "sandbox"
Provides-Extra: dev
Requires-Dist: pytest>=7.0.0; extra == "dev"
Requires-Dist: pytest-cov>=4.0.0; extra == "dev"
Requires-Dist: pytest-asyncio>=0.21.0; extra == "dev"
Requires-Dist: mypy>=1.0.0; extra == "dev"
Requires-Dist: ruff>=0.1.0; extra == "dev"
Requires-Dist: pre-commit>=3.0.0; extra == "dev"
Provides-Extra: docs
Requires-Dist: mkdocs>=1.5.0; extra == "docs"
Requires-Dist: mkdocs-material>=9.0.0; extra == "docs"
Requires-Dist: mkdocstrings[python]>=0.24.0; extra == "docs"
Provides-Extra: hf
Requires-Dist: huggingface-hub>=0.19.0; extra == "hf"
Requires-Dist: datasets>=2.14.0; extra == "hf"
Provides-Extra: all
Requires-Dist: agent-tool-registry[dev,docs,hf,sandbox]; extra == "all"
Dynamic: author
Dynamic: home-page
Dynamic: requires-python
